py_sudoku_maker/__init__.py
py_sudoku_maker/module.py
py_sudoku_maker-1.0.0.dist-info/licenses/LICENSE
py_sudoku_maker-1.0.0.dist-info/METADATA
py_sudoku_maker-1.0.0.dist-info/WHEEL
py_sudoku_maker-1.0.0.dist-info/top_level.txt
py_sudoku_maker-1.0.0.dist-info/RECORD
