Metadata-Version: 2.4
Name: py-sudoku-maker
Version: 1.0.0
Summary: A Python package that creates a completed Sudoku grid
Author-email: Timothy Solnyshkin <timothy.solnyshkin@gmail.com>
License: MIT License
Project-URL: Homepage, https://github.com/ParallelVoid/py-sudoku
Requires-Python: >=3.7
License-File: LICENSE
Dynamic: license-file
